main.py
components/__init__.py
components/ai.py
components/base_component.py
components/consumable.py
components/equipment.py
components/equippable.py
components/fighter.py
components/inventory.py
components/level.py
src/__init__.py
src/actions.py
src/actor.py
src/color.py
src/engine.py
src/entity.py
src/entity_factories.py
src/exceptions.py
src/game_map.py
src/game_world.py
src/input_handlers.py
src/item.py
src/message_log.py
src/procgen.py
src/rectangle.py
src/render_functions.py
src/settings.py
src/setup_game.py
src/tile_types.py
labhack-0.0.2.dist-info/LICENSE
labhack-0.0.2.dist-info/METADATA
labhack-0.0.2.dist-info/WHEEL
labhack-0.0.2.dist-info/top_level.txt
labhack-0.0.2.dist-info/RECORD
