Metadata-Version: 2.1
Name: labhack
Version: 0.0.2
Summary: A super-science roguelike
Home-page: https://github.com/elunna/labhack
Author: Erik Lunna
Author-email: eslunna@gmail.com
License: UNKNOWN
Platform: UNKNOWN
Requires-Python: >=3.6
Requires-Dist: numpy (~=1.19)
Requires-Dist: tcod (~=11.19)
Provides-Extra: dev
Requires-Dist: pytest (>=3.8) ; extra == 'dev'
